rocket/data_types/__init__.py
rocket/data_types/environment_types.py
rocket/data_types/pipeline_notifications_types.py
rocket/data_types/pipeline_types.py
rocket/dtos/__init__.py
rocket/dtos/dependency_dtos.py
rocket/dtos/environment_dtos.py
rocket/dtos/evoml_dtos.py
rocket/dtos/library_dtos.py
rocket/dtos/pipeline_dtos.py
rocket/dtos/system_dtos.py
rocket_client/__init__.py
rocket_client/client.py
rocket_client/environment_client.py
rocket_client/models.py
rocket_client/pipeline_client.py
rocket_client/setup.py
rocket_rest/endpoints/__init__.py
rocket_rest/endpoints/router_prefixes.py
rocket_rest/tos/__init__.py
rocket_rest/tos/dependency_tos.py
rocket_rest/tos/environment_tos.py
rocket_rest/tos/pipeline_tos.py
turintech_evoml_rocket_client-1.2.0.dist-info/LICENSE
turintech_evoml_rocket_client-1.2.0.dist-info/METADATA
turintech_evoml_rocket_client-1.2.0.dist-info/WHEEL
turintech_evoml_rocket_client-1.2.0.dist-info/top_level.txt
turintech_evoml_rocket_client-1.2.0.dist-info/RECORD
